tray_weather/__init__.py
tray_weather/__main__.py
tray_weather/config.py
tray_weather/data_points.py
tray_weather/dialog_custom_location.py
tray_weather/dialog_solar_plot.py
tray_weather/dialog_temperature_plot.py
tray_weather/location.py
tray_weather/main.py
tray_weather/oklahoma.png
tray_weather/solar.py
tray_weather/storms.py
tray_weather/icons/icon.png
trayweathertool_oklahoma-0.9.dist-info/METADATA
trayweathertool_oklahoma-0.9.dist-info/WHEEL
trayweathertool_oklahoma-0.9.dist-info/entry_points.txt
trayweathertool_oklahoma-0.9.dist-info/top_level.txt
trayweathertool_oklahoma-0.9.dist-info/RECORD
